pymsgbox/__init__.py
pymsgbox/_native_win.py
pymsgbox-2.0.0.dist-info/licenses/AUTHORS.txt
pymsgbox-2.0.0.dist-info/licenses/LICENSE.txt
pymsgbox-2.0.0.dist-info/METADATA
pymsgbox-2.0.0.dist-info/WHEEL
pymsgbox-2.0.0.dist-info/top_level.txt
pymsgbox-2.0.0.dist-info/RECORD
