Metadata-Version: 2.4
Name: PyMsgBox
Version: 2.0.0
Summary: A simple, cross-platform, pure Python module for JavaScript-like message boxes.
Author-email: Al Sweigart <al@inventwithpython.com>
Maintainer-email: Al Sweigart <al@inventwithpython.com>
License: Copyright (c) 2014, Al Sweigart
Project-URL: Homepage, https://github.com/asweigart/pymsgbox
Project-URL: Repository, https://github.com/asweigart/pymsgbox
Project-URL: Documentation, https://github.com/asweigart/pymsgbox
Classifier: License :: OSI Approved :: GNU General Public License v3 or later (GPLv3+)
Classifier: Programming Language :: Python
Classifier: Programming Language :: Python :: 3
Classifier: Programming Language :: Python :: 3.4
Classifier: Programming Language :: Python :: 3.5
Classifier: Programming Language :: Python :: 3.6
Classifier: Programming Language :: Python :: 3.7
Classifier: Programming Language :: Python :: 3.8
Classifier: Programming Language :: Python :: 3.9
Requires-Python: >=3.4
License-File: LICENSE.txt
License-File: AUTHORS.txt
Dynamic: license-file
